pymediaroom/__init__.py
pymediaroom/commands.py
pymediaroom/error.py
pymediaroom/notify.py
pymediaroom/remote.py
pymediaroom-0.6.2.dist-info/METADATA
pymediaroom-0.6.2.dist-info/RECORD
pymediaroom-0.6.2.dist-info/WHEEL
pymediaroom-0.6.2.dist-info/top_level.txt
