Metadata-Version: 2.1
Name: pymediaroom
Version: 0.6.2
Summary: Remote control your Mediaroom Set-up-box
Home-page: http://github.com/dgomes/pymediaroom
Author: Diogo Gomes
Author-email: diogogomes@gmail.com
License: MIT
Download-URL: https://github.com/dgomes/pymediaroom/tarball/0.6.2
Platform: UNKNOWN
Requires-Python: >=3.5
Requires-Dist: asyncio
Requires-Dist: async-timeout
Requires-Dist: xmltodict
